odoo/__init__.py
odoo/addons/__init__.py
odoo/addons/hr_phone/__init__.py
odoo/addons/hr_phone/__manifest__.py
odoo/addons/hr_phone/i18n/es.po
odoo/addons/hr_phone/i18n/hr_phone.pot
odoo/addons/hr_phone/i18n/tr.po
odoo/addons/hr_phone/models/__init__.py
odoo/addons/hr_phone/models/hr_employee.py
odoo/addons/hr_phone/security/ir.model.access.csv
odoo12_addon_hr_phone-12.0.1.0.0.dist-info/METADATA
odoo12_addon_hr_phone-12.0.1.0.0.dist-info/RECORD
odoo12_addon_hr_phone-12.0.1.0.0.dist-info/WHEEL
odoo12_addon_hr_phone-12.0.1.0.0.dist-info/top_level.txt
